printipigeon/__init__.py
printipigeon/pigeon.py
printipigeon-0.0.5.dist-info/LICENSE
printipigeon-0.0.5.dist-info/METADATA
printipigeon-0.0.5.dist-info/WHEEL
printipigeon-0.0.5.dist-info/top_level.txt
printipigeon-0.0.5.dist-info/RECORD
