Metadata-Version: 2.1
Name: printipigeon
Version: 0.0.5
Summary: Package for sending images to the printi.me API
Home-page: https://github.com/fons-/printi-pigeon
Author: Fons van der Plas
Author-email: fonsvdplas@gmail.com
License: UNKNOWN
Platform: UNKNOWN
Classifier: Programming Language :: Python :: 3
Classifier: License :: OSI Approved :: MIT License
Classifier: Operating System :: OS Independent
Requires-Dist: requests
